{
  "ngDeps": {
    "1": "",
    "3": [
      {
        "1": "dart:async",
        "5": false
      },
      {
        "1": "../../rate_limit_utils/rate_limit_utils.dart",
        "2": [
          "throttle",
          "throttleGuaranteeLast"
        ],
        "5": false
      },
      {
        "1": "rate_limit.dart",
        "5": false
      }
    ],
    "6": "throttle_stream.dart",
    "7": [
      {
        "1": "../../rate_limit_utils/rate_limit_utils.template.dart",
        "4": "i0"
      },
      {
        "1": "rate_limit.template.dart",
        "4": "i1"
      }
    ]
  },
  "type": {
    "throttleStream": {
      "class": "Identifier",
      "name": "throttleStream",
      "moduleUrl": "asset:angular2_components/lib/src/utils/async/src/throttle_stream.dart",
      "prefix": null,
      "value": null
    }
  },
  "alias": {}
}